{
  "checkpoint_name": "streamlit_batch_20250602_213719",
  "timestamp": "2025-06-03T02:44:31.117209",
  "statistics": {
    "total_processed": 50,
    "successful": 0,
    "failed": 50,
    "skipped": 0,
    "total_time": 431.363868,
    "total_cost": 0.0,
    "errors": [
      {
        "paper_id": "2505.24878v1",
        "error": "Timeout",
        "timestamp": "2025-06-03T02:38:19.758737"
      },
      {
        "paper_id": "2505.24858v1",
        "error": "Timeout",
        "timestamp": "2025-06-03T02:39:55.357890"
      },
      {
        "paper_id": "2505.24830v1",
        "error": "Timeout",
        "timestamp": "2025-06-03T02:41:33.653567"
      },
      {
        "paper_id": "2505.24779v1",
        "error": "Timeout",
        "timestamp": "2025-06-03T02:42:49.499717"
      },
      {
        "paper_id": "2505.24731v1",
        "error": "Timeout",
        "timestamp": "2025-06-03T02:43:52.369094"
      }
    ]
  },
  "storage_stats": {
    "total_papers": 50,
    "total_insights": 49,
    "papers_with_code": 5,
    "complexity_distribution": {
      "high": 2,
      "medium": 8
    },
    "study_type_distribution": {
      "empirical": 10
    },
    "average_quality_score": 0.637,
    "total_extraction_cost": 0.38
  }
}